svdawg/__init__.py
svdawg/svdawg.py
svdawg-0.5.dist-info/LICENSE
svdawg-0.5.dist-info/METADATA
svdawg-0.5.dist-info/WHEEL
svdawg-0.5.dist-info/top_level.txt
svdawg-0.5.dist-info/RECORD
