Metadata-Version: 2.1
Name: svdawg
Version: 0.5
Summary: SVD accessories, widgets, and graphics
Home-page: https://github.com/SpacemanSpiff7/svdawg
Author: Simone Longo
Author-email: s.longo@utah.edu
License: MIT
Platform: UNKNOWN
Requires-Python: >=3.6
Requires-Dist: pandas
Requires-Dist: numpy
Requires-Dist: seaborn
Requires-Dist: matplotlib
Requires-Dist: sklearn
